blocklint/__init__.py
blocklint/__main__.py
blocklint/main.py
blocklint/version.py
blocklint-0.2.5.dist-info/LICENSE
blocklint-0.2.5.dist-info/METADATA
blocklint-0.2.5.dist-info/WHEEL
blocklint-0.2.5.dist-info/entry_points.txt
blocklint-0.2.5.dist-info/top_level.txt
blocklint-0.2.5.dist-info/RECORD
