Metadata-Version: 2.1
Name: blocklint
Version: 0.2.5
Summary: Lint for blocklisted words.
Home-page: https://github.com/PrincetonUniversity/blocklint
Author: Troy Comi
Author-email: tcomi@princeton.edu
License: MIT License
Classifier: Development Status :: 4 - Beta
Classifier: Intended Audience :: Developers
Classifier: Intended Audience :: Information Technology
Classifier: License :: OSI Approved :: MIT License
Classifier: Operating System :: Microsoft :: Windows
Classifier: Operating System :: MacOS
Classifier: Operating System :: POSIX
Classifier: Operating System :: Unix
Classifier: Programming Language :: Python
Classifier: Programming Language :: Python :: 2.7
Classifier: Programming Language :: Python :: 3.5
Classifier: Programming Language :: Python :: 3.6
Classifier: Programming Language :: Python :: 3.7
Classifier: Programming Language :: Python :: 3.8
Classifier: Topic :: Software Development
Classifier: Topic :: Utilities
Requires-Python: !=3.0,!=3.1,!=3.2,!=3.3,!=3.4,>=2.7
License-File: LICENSE
Provides-Extra: test
Requires-Dist: tox ; extra == 'test'
Requires-Dist: pytest ; extra == 'test'
Requires-Dist: pytest-mock ; extra == 'test'
